cronvisio/__init__.py
cronvisio/cli.py
cronvisio/monitor/__init__.py
cronvisio/monitor/amazon_kindle_quotes.py
cronvisio/monitor/automysqlbackup.py
cronvisio/monitor/borgbackup.py
cronvisio/monitor/postfix.py
cronvisio/monitor/tlsreport.py
cronvisio/notifier/__init__.py
cronvisio/notifier/matrix.py
cronvisio/notifier/stdout.py
cronvisio-0.9.0.dist-info/LICENSE
cronvisio-0.9.0.dist-info/METADATA
cronvisio-0.9.0.dist-info/WHEEL
cronvisio-0.9.0.dist-info/entry_points.txt
cronvisio-0.9.0.dist-info/RECORD
